print_numbers/__init__.py
print_numbers/print_number.py
echristie_test-0.0.5.dist-info/METADATA
echristie_test-0.0.5.dist-info/WHEEL
echristie_test-0.0.5.dist-info/top_level.txt
echristie_test-0.0.5.dist-info/RECORD
