Metadata-Version: 2.1
Name: echristie-test
Version: 0.0.5
Summary: Temp Package
Author: Edwin
Requires-Python: >=3.6
